ldsso/__init__.py
ldsso/ld_sso.py
ldsso-0.0.10.dist-info/METADATA
ldsso-0.0.10.dist-info/WHEEL
ldsso-0.0.10.dist-info/top_level.txt
ldsso-0.0.10.dist-info/RECORD
